[
  {
    "anonymous": false,
    "inputs": [
      {
        "indexed": true,
        "internalType": "bytes32",
        "name": "perpetualId",
        "type": "bytes32"
      },
      {
        "indexed": true,
        "internalType": "address",
        "name": "trader",
        "type": "address"
      },
      {
        "indexed": false,
        "internalType": "int128",
        "name": "limitPrice",
        "type": "int128"
      },
      {
        "indexed": false,
        "internalType": "int128",
        "name": "triggerPrice",
        "type": "int128"
      },
      {
        "indexed": false,
        "internalType": "bytes32",
        "name": "digest",
        "type": "bytes32"
      }
    ],
    "name": "PerpetualLimitOrderCreated",
    "type": "event"
  },
  {
    "inputs": [
      {
        "internalType": "uint256",
        "name": "",
        "type": "uint256"
      }
    ],
    "name": "allDigests",
    "outputs": [
      {
        "internalType": "bytes32",
        "name": "",
        "type": "bytes32"
      }
    ],
    "stateMutability": "view",
    "type": "function"
  },
  {
    "inputs": [
      {
        "internalType": "uint256",
        "name": "page",
        "type": "uint256"
      },
      {
        "internalType": "uint256",
        "name": "limit",
        "type": "uint256"
      }
    ],
    "name": "allLimitDigests",
    "outputs": [
      {
        "internalType": "bytes32[]",
        "name": "",
        "type": "bytes32[]"
      }
    ],
    "stateMutability": "view",
    "type": "function"
  },
  {
    "inputs": [
      {
        "internalType": "bytes32",
        "name": "_digest",
        "type": "bytes32"
      },
      {
        "internalType": "bytes",
        "name": "_signature",
        "type": "bytes"
      }
    ],
    "name": "cancelLimitOrder",
    "outputs": [],
    "stateMutability": "nonpayable",
    "type": "function"
  },
  {
    "inputs": [
      {
        "components": [
          {
            "internalType": "bytes32",
            "name": "iPerpetualId",
            "type": "bytes32"
          },
          {
            "internalType": "address",
            "name": "traderAddr",
            "type": "address"
          },
          {
            "internalType": "int128",
            "name": "fAmount",
            "type": "int128"
          },
          {
            "internalType": "int128",
            "name": "fLimitPrice",
            "type": "int128"
          },
          {
            "internalType": "int128",
            "name": "fTriggerPrice",
            "type": "int128"
          },
          {
            "internalType": "uint256",
            "name": "iDeadline",
            "type": "uint256"
          },
          {
            "internalType": "address",
            "name": "referrerAddr",
            "type": "address"
          },
          {
            "internalType": "uint32",
            "name": "flags",
            "type": "uint32"
          },
          {
            "internalType": "int128",
            "name": "fLeverage",
            "type": "int128"
          },
          {
            "internalType": "uint256",
            "name": "createdTimestamp",
            "type": "uint256"
          }
        ],
        "internalType": "struct IPerpetualOrder.Order",
        "name": "_order",
        "type": "tuple"
      },
      {
        "internalType": "bytes",
        "name": "signature",
        "type": "bytes"
      },
      {
        "internalType": "uint256",
        "name": "_allowance",
        "type": "uint256"
      }
    ],
    "name": "createLimitOrder",
    "outputs": [],
    "stateMutability": "nonpayable",
    "type": "function"
  },
  {
    "inputs": [
      {
        "internalType": "address",
        "name": "",
        "type": "address"
      },
      {
        "internalType": "uint256",
        "name": "",
        "type": "uint256"
      }
    ],
    "name": "digestsOfTrader",
    "outputs": [
      {
        "internalType": "bytes32",
        "name": "",
        "type": "bytes32"
      }
    ],
    "stateMutability": "view",
    "type": "function"
  },
  {
    "inputs": [
      {
        "components": [
          {
            "internalType": "bytes32",
            "name": "iPerpetualId",
            "type": "bytes32"
          },
          {
            "internalType": "address",
            "name": "traderAddr",
            "type": "address"
          },
          {
            "internalType": "int128",
            "name": "fAmount",
            "type": "int128"
          },
          {
            "internalType": "int128",
            "name": "fLimitPrice",
            "type": "int128"
          },
          {
            "internalType": "int128",
            "name": "fTriggerPrice",
            "type": "int128"
          },
          {
            "internalType": "uint256",
            "name": "iDeadline",
            "type": "uint256"
          },
          {
            "internalType": "address",
            "name": "referrerAddr",
            "type": "address"
          },
          {
            "internalType": "uint32",
            "name": "flags",
            "type": "uint32"
          },
          {
            "internalType": "int128",
            "name": "fLeverage",
            "type": "int128"
          },
          {
            "internalType": "uint256",
            "name": "createdTimestamp",
            "type": "uint256"
          }
        ],
        "internalType": "struct IPerpetualOrder.Order",
        "name": "_order",
        "type": "tuple"
      }
    ],
    "name": "executeLimitOrder",
    "outputs": [],
    "stateMutability": "nonpayable",
    "type": "function"
  },
  {
    "inputs": [
      {
        "internalType": "address",
        "name": "trader",
        "type": "address"
      },
      {
        "internalType": "uint256",
        "name": "offset",
        "type": "uint256"
      },
      {
        "internalType": "uint256",
        "name": "limit",
        "type": "uint256"
      }
    ],
    "name": "getOrders",
    "outputs": [
      {
        "components": [
          {
            "internalType": "bytes32",
            "name": "iPerpetualId",
            "type": "bytes32"
          },
          {
            "internalType": "address",
            "name": "traderAddr",
            "type": "address"
          },
          {
            "internalType": "int128",
            "name": "fAmount",
            "type": "int128"
          },
          {
            "internalType": "int128",
            "name": "fLimitPrice",
            "type": "int128"
          },
          {
            "internalType": "int128",
            "name": "fTriggerPrice",
            "type": "int128"
          },
          {
            "internalType": "uint256",
            "name": "iDeadline",
            "type": "uint256"
          },
          {
            "internalType": "address",
            "name": "referrerAddr",
            "type": "address"
          },
          {
            "internalType": "uint32",
            "name": "flags",
            "type": "uint32"
          },
          {
            "internalType": "int128",
            "name": "fLeverage",
            "type": "int128"
          },
          {
            "internalType": "uint256",
            "name": "createdTimestamp",
            "type": "uint256"
          }
        ],
        "internalType": "struct IPerpetualOrder.Order[]",
        "name": "orders",
        "type": "tuple[]"
      }
    ],
    "stateMutability": "view",
    "type": "function"
  },
  {
    "inputs": [
      {
        "internalType": "bytes32",
        "name": "digest",
        "type": "bytes32"
      }
    ],
    "name": "getSignature",
    "outputs": [
      {
        "internalType": "bytes",
        "name": "signature",
        "type": "bytes"
      }
    ],
    "stateMutability": "view",
    "type": "function"
  },
  {
    "inputs": [
      {
        "internalType": "bytes32",
        "name": "digest",
        "type": "bytes32"
      }
    ],
    "name": "getTrader",
    "outputs": [
      {
        "internalType": "address",
        "name": "trader",
        "type": "address"
      }
    ],
    "stateMutability": "view",
    "type": "function"
  },
  {
    "inputs": [
      {
        "internalType": "address",
        "name": "_perpetualManagerAddr",
        "type": "address"
      },
      {
        "internalType": "bytes32",
        "name": "_perpetualId",
        "type": "bytes32"
      }
    ],
    "name": "initialize",
    "outputs": [],
    "stateMutability": "nonpayable",
    "type": "function"
  },
  {
    "inputs": [],
    "name": "lastOrderHash",
    "outputs": [
      {
        "internalType": "bytes32",
        "name": "",
        "type": "bytes32"
      }
    ],
    "stateMutability": "view",
    "type": "function"
  },
  {
    "inputs": [
      {
        "internalType": "address",
        "name": "trader",
        "type": "address"
      },
      {
        "internalType": "uint256",
        "name": "page",
        "type": "uint256"
      },
      {
        "internalType": "uint256",
        "name": "limit",
        "type": "uint256"
      }
    ],
    "name": "limitDigestsOfTrader",
    "outputs": [
      {
        "internalType": "bytes32[]",
        "name": "",
        "type": "bytes32[]"
      }
    ],
    "stateMutability": "view",
    "type": "function"
  },
  {
    "inputs": [],
    "name": "marginToken",
    "outputs": [
      {
        "internalType": "contract IERC20Upgradeable",
        "name": "",
        "type": "address"
      }
    ],
    "stateMutability": "view",
    "type": "function"
  },
  {
    "inputs": [
      {
        "internalType": "bytes32",
        "name": "",
        "type": "bytes32"
      }
    ],
    "name": "nextOrderHash",
    "outputs": [
      {
        "internalType": "bytes32",
        "name": "",
        "type": "bytes32"
      }
    ],
    "stateMutability": "view",
    "type": "function"
  },
  {
    "inputs": [],
    "name": "numberOfAllDigests",
    "outputs": [
      {
        "internalType": "uint256",
        "name": "",
        "type": "uint256"
      }
    ],
    "stateMutability": "view",
    "type": "function"
  },
  {
    "inputs": [
      {
        "internalType": "address",
        "name": "trader",
        "type": "address"
      }
    ],
    "name": "numberOfDigestsOfTrader",
    "outputs": [
      {
        "internalType": "uint256",
        "name": "",
        "type": "uint256"
      }
    ],
    "stateMutability": "view",
    "type": "function"
  },
  {
    "inputs": [],
    "name": "numberOfOrderBookDigests",
    "outputs": [
      {
        "internalType": "uint256",
        "name": "",
        "type": "uint256"
      }
    ],
    "stateMutability": "view",
    "type": "function"
  },
  {
    "inputs": [],
    "name": "orderCount",
    "outputs": [
      {
        "internalType": "uint256",
        "name": "",
        "type": "uint256"
      }
    ],
    "stateMutability": "view",
    "type": "function"
  },
  {
    "inputs": [
      {
        "internalType": "bytes32",
        "name": "",
        "type": "bytes32"
      }
    ],
    "name": "orderOfDigest",
    "outputs": [
      {
        "internalType": "bytes32",
        "name": "iPerpetualId",
        "type": "bytes32"
      },
      {
        "internalType": "address",
        "name": "traderAddr",
        "type": "address"
      },
      {
        "internalType": "int128",
        "name": "fAmount",
        "type": "int128"
      },
      {
        "internalType": "int128",
        "name": "fLimitPrice",
        "type": "int128"
      },
      {
        "internalType": "int128",
        "name": "fTriggerPrice",
        "type": "int128"
      },
      {
        "internalType": "uint256",
        "name": "iDeadline",
        "type": "uint256"
      },
      {
        "internalType": "address",
        "name": "referrerAddr",
        "type": "address"
      },
      {
        "internalType": "uint32",
        "name": "flags",
        "type": "uint32"
      },
      {
        "internalType": "int128",
        "name": "fLeverage",
        "type": "int128"
      },
      {
        "internalType": "uint256",
        "name": "createdTimestamp",
        "type": "uint256"
      }
    ],
    "stateMutability": "view",
    "type": "function"
  },
  {
    "inputs": [
      {
        "internalType": "bytes32",
        "name": "",
        "type": "bytes32"
      }
    ],
    "name": "orderSignature",
    "outputs": [
      {
        "internalType": "bytes",
        "name": "",
        "type": "bytes"
      }
    ],
    "stateMutability": "view",
    "type": "function"
  },
  {
    "inputs": [],
    "name": "perpManager",
    "outputs": [
      {
        "internalType": "contract IPerpetualManager",
        "name": "",
        "type": "address"
      }
    ],
    "stateMutability": "view",
    "type": "function"
  },
  {
    "inputs": [],
    "name": "perpetualId",
    "outputs": [
      {
        "internalType": "bytes32",
        "name": "",
        "type": "bytes32"
      }
    ],
    "stateMutability": "view",
    "type": "function"
  },
  {
    "inputs": [
      {
        "internalType": "bytes32",
        "name": "_startAfter",
        "type": "bytes32"
      },
      {
        "internalType": "uint256",
        "name": "_numElements",
        "type": "uint256"
      }
    ],
    "name": "pollLimitOrders",
    "outputs": [
      {
        "components": [
          {
            "internalType": "bytes32",
            "name": "iPerpetualId",
            "type": "bytes32"
          },
          {
            "internalType": "address",
            "name": "traderAddr",
            "type": "address"
          },
          {
            "internalType": "int128",
            "name": "fAmount",
            "type": "int128"
          },
          {
            "internalType": "int128",
            "name": "fLimitPrice",
            "type": "int128"
          },
          {
            "internalType": "int128",
            "name": "fTriggerPrice",
            "type": "int128"
          },
          {
            "internalType": "uint256",
            "name": "iDeadline",
            "type": "uint256"
          },
          {
            "internalType": "address",
            "name": "referrerAddr",
            "type": "address"
          },
          {
            "internalType": "uint32",
            "name": "flags",
            "type": "uint32"
          },
          {
            "internalType": "int128",
            "name": "fLeverage",
            "type": "int128"
          },
          {
            "internalType": "uint256",
            "name": "createdTimestamp",
            "type": "uint256"
          }
        ],
        "internalType": "struct IPerpetualOrder.Order[]",
        "name": "orders",
        "type": "tuple[]"
      },
      {
        "internalType": "bytes32[]",
        "name": "orderHashes",
        "type": "bytes32[]"
      }
    ],
    "stateMutability": "view",
    "type": "function"
  },
  {
    "inputs": [
      {
        "internalType": "bytes32",
        "name": "",
        "type": "bytes32"
      }
    ],
    "name": "prevOrderHash",
    "outputs": [
      {
        "internalType": "bytes32",
        "name": "",
        "type": "bytes32"
      }
    ],
    "stateMutability": "view",
    "type": "function"
  }
]
